hardware/verilog/tpu_simple.v
`timescale 1ns / 1ps

// Simplified TPU for testing - Direct matrix multiplication without complex buffering
module tpu_simple #(
    parameter SIZE = 4,
    parameter DATA_WIDTH = 8,
    parameter ACC_WIDTH = 32
)(
    input wire clk,
    input wire rst_n,
    input wire start,
    input wire [7:0] matrix_size,
    
    // Direct matrix inputs for testing
    input wire signed [DATA_WIDTH-1:0] matrix_a [0:SIZE-1][0:SIZE-1],
    input wire signed [DATA_WIDTH-1:0] matrix_b [0:SIZE-1][0:SIZE-1],
    
    // Output matrix
    output reg signed [ACC_WIDTH-1:0] matrix_c [0:SIZE-1][0:SIZE-1],
    
    // Status
    output reg busy,
    output reg done
);

    // State machine
    localparam IDLE = 2'b00;
    localparam COMPUTE = 2'b01;
    localparam DONE = 2'b10;
    
    reg [1:0] state;
    reg [7:0] k_counter;  // K dimension counter
    
    integer i, j;
    
    always @(posedge clk or negedge rst_n) begin
        if (!rst_n) begin
            state <= IDLE;
            busy <= 1'b0;
            done <= 1'b0;
            k_counter <= 8'd0;
            
            for (i = 0; i < SIZE; i = i + 1) begin
                for (j = 0; j < SIZE; j = j + 1) begin
                    matrix_c[i][j] <= {ACC_WIDTH{1'b0}};
                end
            end
            
        end else begin
            case (state)
                IDLE: begin
                    done <= 1'b0;
                    if (start) begin
                        busy <= 1'b1;
                        k_counter <= 8'd0;
                        state <= COMPUTE;
                        
                        // Clear output matrix
                        for (i = 0; i < SIZE; i = i + 1) begin
                            for (j = 0; j < SIZE; j = j + 1) begin
                                matrix_c[i][j] <= {ACC_WIDTH{1'b0}};
                            end
                        end
                    end
                end
                
                COMPUTE: begin
                    // Perform one iteration of k: C[i][j] += A[i][k] * B[k][j]
                    for (i = 0; i < matrix_size; i = i + 1) begin
                        for (j = 0; j < matrix_size; j = j + 1) begin
                            matrix_c[i][j] <= matrix_c[i][j] + 
                                            (matrix_a[i][k_counter] * matrix_b[k_counter][j]);
                        end
                    end
                    
                    if (k_counter >= matrix_size - 1) begin
                        state <= DONE;
                    end else begin
                        k_counter <= k_counter + 1;
                    end
                end
                
                DONE: begin
                    busy <= 1'b0;
                    done <= 1'b1;
                    state <= IDLE;
                end
            endcase
        end
    end

endmodule

hardware/verilog/tpu_simple_testbench.v
`timescale 1ns / 1ps

// Simple Testbench for TPU
module tpu_simple_testbench;

    parameter SIZE = 4;
    parameter DATA_WIDTH = 8;
    parameter ACC_WIDTH = 32;
    parameter CLK_PERIOD = 10;
    
    reg clk;
    reg rst_n;
    reg start;
    reg [7:0] matrix_size;
    
    reg signed [DATA_WIDTH-1:0] matrix_a [0:SIZE-1][0:SIZE-1];
    reg signed [DATA_WIDTH-1:0] matrix_b [0:SIZE-1][0:SIZE-1];
    wire signed [ACC_WIDTH-1:0] matrix_c [0:SIZE-1][0:SIZE-1];
    
    wire busy;
    wire done;
    
    integer i, j;
    
    // Clock generation
    initial begin
        clk = 0;
        forever #(CLK_PERIOD/2) clk = ~clk;
    end
    
    // DUT
    tpu_simple #(
        .SIZE(SIZE),
        .DATA_WIDTH(DATA_WIDTH),
        .ACC_WIDTH(ACC_WIDTH)
    ) dut (
        .clk(clk),
        .rst_n(rst_n),
        .start(start),
        .matrix_size(matrix_size),
        .matrix_a(matrix_a),
        .matrix_b(matrix_b),
        .matrix_c(matrix_c),
        .busy(busy),
        .done(done)
    );
    
    // Test
    initial begin
        $dumpfile("tpu_simple_tb.vcd");
        $dumpvars(0, tpu_simple_testbench);
        
        // Initialize
        rst_n = 0;
        start = 0;
        matrix_size = 2;
        
        // Initialize matrices to zero
        for (i = 0; i < SIZE; i = i + 1) begin
            for (j = 0; j < SIZE; j = j + 1) begin
                matrix_a[i][j] = 0;
                matrix_b[i][j] = 0;
            end
        end
        
        #(CLK_PERIOD*5);
        rst_n = 1;
        #(CLK_PERIOD*2);
        
        $display("\n=== TPU Simple Testbench ===\n");
        
        // Test Case 1: 2x2 matrix multiplication
        // A = [1 2]    B = [5 6]
        //     [3 4]        [7 8]
        // C = [19 22]
        //     [43 50]
        
        $display("Test Case 1: Basic 2x2 Matrix Multiplication");
        $display("Matrix A:");
        matrix_a[0][0] = 1; matrix_a[0][1] = 2;
        matrix_a[1][0] = 3; matrix_a[1][1] = 4;
        $display("  [%0d %0d]", matrix_a[0][0], matrix_a[0][1]);
        $display("  [%0d %0d]", matrix_a[1][0], matrix_a[1][1]);
        
        $display("Matrix B:");
        matrix_b[0][0] = 5; matrix_b[0][1] = 6;
        matrix_b[1][0] = 7; matrix_b[1][1] = 8;
        $display("  [%0d %0d]", matrix_b[0][0], matrix_b[0][1]);
        $display("  [%0d %0d]", matrix_b[1][0], matrix_b[1][1]);
        
        matrix_size = 2;
        start = 1;
        #CLK_PERIOD;
        start = 0;
        
        wait(done == 1);
        #(CLK_PERIOD*2);
        
        $display("\nResult Matrix C:");
        $display("  [%0d %0d]", $signed(matrix_c[0][0]), $signed(matrix_c[0][1]));
        $display("  [%0d %0d]", $signed(matrix_c[1][0]), $signed(matrix_c[1][1]));
        
        $display("\nExpected:");
        $display("  [19 22]");
        $display("  [43 50]");
        
        if (matrix_c[0][0] == 19 && matrix_c[0][1] == 22 && 
            matrix_c[1][0] == 43 && matrix_c[1][1] == 50) begin
            $display("\n✓ TEST PASSED!\n");
        end else begin
            $display("\n✗ TEST FAILED!\n");
        end
        
        #(CLK_PERIOD*10);
        
        // Test Case 2: Identity matrix
        $display("\nTest Case 2: Identity Matrix");
        
        rst_n = 0;
        #(CLK_PERIOD*2);
        rst_n = 1;
        #(CLK_PERIOD*2);
        
        $display("Matrix A:");
        matrix_a[0][0] = 5; matrix_a[0][1] = 6;
        matrix_a[1][0] = 7; matrix_a[1][1] = 8;
        $display("  [%0d %0d]", matrix_a[0][0], matrix_a[0][1]);
        $display("  [%0d %0d]", matrix_a[1][0], matrix_a[1][1]);
        
        $display("Matrix B (Identity):");
        matrix_b[0][0] = 1; matrix_b[0][1] = 0;
        matrix_b[1][0] = 0; matrix_b[1][1] = 1;
        $display("  [%0d %0d]", matrix_b[0][0], matrix_b[0][1]);
        $display("  [%0d %0d]", matrix_b[1][0], matrix_b[1][1]);
        
        matrix_size = 2;
        start = 1;
        #CLK_PERIOD;
        start = 0;
        
        wait(done == 1);
        #(CLK_PERIOD*2);
        
        $display("\nResult Matrix C:");
        $display("  [%0d %0d]", $signed(matrix_c[0][0]), $signed(matrix_c[0][1]));
        $display("  [%0d %0d]", $signed(matrix_c[1][0]), $signed(matrix_c[1][1]));
        
        $display("\nExpected (same as A):");
        $display("  [5 6]");
        $display("  [7 8]");
        
        if (matrix_c[0][0] == 5 && matrix_c[0][1] == 6 && 
            matrix_c[1][0] == 7 && matrix_c[1][1] == 8) begin
            $display("\n✓ TEST PASSED!\n");
        end else begin
            $display("\n✗ TEST FAILED!\n");
        end
        
        #(CLK_PERIOD*20);
        
        $display("\n=== All Tests Complete ===\n");
        $finish;
    end
    
    // Timeout
    initial begin
        #(CLK_PERIOD*1000);
        $display("\nERROR: Timeout!");
        $finish;
    end

endmodule

tpu_simple_tb.vcd
$date
	Sat Nov 15 20:35:59 2025
$end
$version
	Icarus Verilog
$end
$timescale
	1ps
$end
$scope module tpu_simple_testbench $end
$var wire 1 ! done $end
$var wire 1 " busy $end
$var parameter 32 # ACC_WIDTH $end
$var parameter 32 $ CLK_PERIOD $end
$var parameter 32 % DATA_WIDTH $end
$var parameter 32 & SIZE $end
$var reg 1 ' clk $end
$var reg 8 ( matrix_size [7:0] $end
$var reg 1 ) rst_n $end
$var reg 1 * start $end
$var integer 32 + i [31:0] $end
$var integer 32 , j [31:0] $end
$scope module dut $end
$var wire 1 ' clk $end
$var wire 8 - matrix_size [7:0] $end
$var wire 1 ) rst_n $end
$var wire 1 * start $end
$var parameter 32 . ACC_WIDTH $end
$var parameter 2 / COMPUTE $end
$var parameter 32 0 DATA_WIDTH $end
$var parameter 2 1 DONE $end
$var parameter 2 2 IDLE $end
$var parameter 32 3 SIZE $end
$var reg 1 " busy $end
$var reg 1 ! done $end
$var reg 8 4 k_counter [7:0] $end
$var reg 2 5 state [1:0] $end
$var integer 32 6 i [31:0] $end
$var integer 32 7 j [31:0] $end
$upscope $end
$upscope $end
$enddefinitions $end
$comment Show the parameter values. $end
$dumpall
b100 3
b0 2
b10 1
b1000 0
b1 /
b100000 .
b100 &
b1000 %
b1010 $
b100000 #
$end
#0
$dumpvars
b100 7
b100 6
b0 5
b0 4
b10 -
b100 ,
b100 +
0*
0)
b10 (
0'
0"
0!
$end
#5000
b100 7
b100 6
1'
#10000
0'
#15000
b100 7
b100 6
1'
#20000
0'
#25000
b100 7
b100 6
1'
#30000
0'
#35000
b100 7
b100 6
1'
#40000
0'
#45000
b100 7
b100 6
1'
#50000
0'
1)
#55000
1'
#60000
0'
#65000
1'
#70000
0'
1*
#75000
b1 5
1"
b100 7
b100 6
1'
#80000
0'
0*
#85000
b1 4
b10 7
b10 6
1'
#90000
0'
#95000
b10 5
b10 7
b10 6
1'
#100000
0'
#105000
b0 5
1!
0"
1'
#110000
0'
#115000
0!
1'
#120000
0'
#125000
1'
#130000
0'
#135000
1'
#140000
0'
#145000
1'
#150000
0'
#155000
1'
#160000
0'
#165000
1'
#170000
0'
#175000
1'
#180000
0'
#185000
1'
#190000
0'
#195000
1'
#200000
0'
#205000
1'
#210000
0'
#215000
1'
#220000
0'
#225000
b0 4
b100 7
b100 6
1'
0)
#230000
0'
#235000
b100 7
b100 6
1'
#240000
0'
#245000
1'
1)
#250000
0'
#255000
1'
#260000
0'
#265000
b1 5
1"
b100 7
b100 6
1'
1*
#270000
0'
#275000
b1 4
b10 7
b10 6
1'
0*
#280000
0'
#285000
b10 5
b10 7
b10 6
1'
#290000
0'
#295000
b0 5
1!
0"
1'
#300000
0'
#305000
0!
1'
